st_cookie/__init__.py
st_cookie/_core.py
st_cookie-1.0.0.dist-info/METADATA
st_cookie-1.0.0.dist-info/WHEEL
st_cookie-1.0.0.dist-info/top_level.txt
st_cookie-1.0.0.dist-info/RECORD
